odoo8_addon_l10n_ma_state-8.0.0.1.0.99.dev13-py2.7-nspkg.pth
odoo_addons/l10n_ma_state/__openerp__.py
odoo_addons/l10n_ma_state/__init__.py
odoo_addons/l10n_ma_state/README.rst
odoo_addons/l10n_ma_state/data/res_country_state_data.yml
odoo_addons/l10n_ma_state/static/description/icon.png
odoo_addons/l10n_ma_state/static/src/img/screenshots/1.png
odoo8_addon_l10n_ma_state-8.0.0.1.0.99.dev13.dist-info/top_level.txt
odoo8_addon_l10n_ma_state-8.0.0.1.0.99.dev13.dist-info/WHEEL
odoo8_addon_l10n_ma_state-8.0.0.1.0.99.dev13.dist-info/RECORD
odoo8_addon_l10n_ma_state-8.0.0.1.0.99.dev13.dist-info/metadata.json
odoo8_addon_l10n_ma_state-8.0.0.1.0.99.dev13.dist-info/DESCRIPTION.rst
odoo8_addon_l10n_ma_state-8.0.0.1.0.99.dev13.dist-info/METADATA
odoo8_addon_l10n_ma_state-8.0.0.1.0.99.dev13.dist-info/namespace_packages.txt
