Metadata-Version: 2.0
Name: odoo8-addon-l10n-ma-state
Version: 8.0.0.1.0.99.dev13
Summary: Populate Database with the 12 Moroccan States (Régions)
Home-page: http://www.agoradeveloppement.com
Author: UNKNOWN
Author-email: UNKNOWN
License: AGPL-3
Platform: UNKNOWN
Requires-Dist: odoo (<9.0a,>=8.0a)
Classifier: Programming Language :: Python :: 2.7
Classifier: Framework :: Odoo
Classifier: License :: OSI Approved :: GNU Affero General Public License v3
